setup.cfg
setup.py
pkt/__init__.py
pkt/core.py
pkt/mixins.py
pkt/version.py
pkt.egg-info/PKG-INFO
pkt.egg-info/SOURCES.txt
pkt.egg-info/dependency_links.txt
pkt.egg-info/requires.txt
pkt.egg-info/top_level.txt