Metadata-Version: 1.0
Name: pkt
Version: 0.0.1
Summary: Pkt: Abstract network package
Home-page: https://github.com/netanelrevah/pkt
Author: netanelrevah
Author-email: netanelrevah@outlook.com
License: GNU General Public License, version 2
Keywords: network packet pkt
Platform: UNKNOWN
